<!DOCTYPE ui:UiBinder SYSTEM "http://dl.google.com/gwt/DTD/xhtml.ent">
<ui:UiBinder xmlns:ui="urn:ui:com.google.gwt.uibinder"
             xmlns:g="urn:import:com.google.gwt.user.client.ui"
             xmlns:b="urn:import:org.gwtbootstrap3.client.ui"
             ui:generateFormat='com.google.gwt.i18n.rebind.format.PropertiesFormat'
             ui:generateKeys="com.google.gwt.i18n.server.keygen.MD5KeyGenerator"
             ui:generateLocales="default">

    <ui:with field="res" type="online.shashki.rus.client.resources.AppResources"/>

    <g:HTMLPanel ui:field="loginContainer">
        <b:Row>
            <b:Column size="MD_8" offset="MD_2">
                <b:Row>
                    <b:Column size="MD_3">
                        <b:Icon type="SIGN_IN" size="TIMES5" addStyleNames="{res.style.alignHorizontal}"/>
                    </b:Column>
                    <b:Column size="MD_3">
                        <b:Anchor href="/rus/OAuthVKServlet" icon="VK" iconSize="TIMES5"
                                  addStyleNames="{res.style.alignHorizontal}"/>
                    </b:Column>
                    <b:Column size="MD_3">
                        <b:Anchor href="/rus/OAuthGoogleServlet" icon="GOOGLE" iconSize="TIMES5"
                                  addStyleNames="{res.style.alignHorizontal}"/>
                    </b:Column>
                    <b:Column size="MD_3">
                        <b:Anchor href="/rus/OAuthFacebookServlet" icon="FACEBOOK_OFFICIAL" iconSize="TIMES5"
                                  addStyleNames="{res.style.alignHorizontal}"/>
                    </b:Column>
                </b:Row>
            </b:Column>
        </b:Row>
    </g:HTMLPanel>

</ui:UiBinder>
